{
  "version": "1.2.0",
  "title": "Historisk hockey-prestasjon",
  "author": "NRK",
  "podcastName": "Nyhetsmorgen",
  "chapters": [
    {
      "startTime": 2,
      "title": "Åpning 06:30",
      "img": "https://nrk-od-world-17.akamaized.net/open/ps/nnfa/nnfa05052926/e74408c7-23.smil/thumb.jpg?t=28&scale=480x270&v=high"
    },
    {
      "startTime": 88,
      "title": "Mener frontfaget fungerer dårlig",
      "img": "https://nrk-od-world-17.akamaized.net/open/ps/nnfa/nnfa05052926/e74408c7-23.smil/thumb.jpg?t=113&scale=480x270&v=high"
    },
    {
      "startTime": 135,
      "title": "Fortsatt fare for streik i staten",
      "img": "https://nrk-od-world-17.akamaized.net/open/ps/nnfa/nnfa05052926/e74408c7-23.smil/thumb.jpg?t=160&scale=480x270&v=high"
    },
    {
      "startTime": 346,
      "title": "Siste nytt",
      "img": "https://nrk-od-world-17.akamaized.net/open/ps/nnfa/nnfa05052926/e74408c7-23.smil/thumb.jpg?t=372&scale=480x270&v=high"
    },
    {
      "startTime": 493,
      "title": "Alkohol på hvileplasser",
      "img": "https://nrk-od-world-17.akamaized.net/open/ps/nnfa/nnfa05052926/e74408c7-23.smil/thumb.jpg?t=518&scale=480x270&v=high"
    },
    {
      "startTime": 646,
      "title": "Radikalisering barn og unge",
      "img": "https://nrk-od-world-17.akamaized.net/open/ps/nnfa/nnfa05052926/e74408c7-23.smil/thumb.jpg?t=672&scale=480x270&v=high"
    },
    {
      "startTime": 779,
      "title": "Overskrifter 06:45",
      "img": "https://nrk-od-world-17.akamaized.net/open/ps/nnfa/nnfa05052926/e74408c7-23.smil/thumb.jpg?t=804&scale=480x270&v=high"
    },
    {
      "startTime": 816,
      "title": "Ødegaard og mesterligafinalen",
      "img": "https://nrk-od-world-17.akamaized.net/open/ps/nnfa/nnfa05052926/e74408c7-23.smil/thumb.jpg?t=841&scale=480x270&v=high"
    },
    {
      "startTime": 1202,
      "title": "Historisk semifinale i ishockey",
      "img": "https://nrk-od-world-17.akamaized.net/open/ps/nnfa/nnfa05052926/e74408c7-23.smil/thumb.jpg?t=1227&scale=480x270&v=high"
    },
    {
      "startTime": 1303,
      "title": "Andreas Kravik om hockey-seier",
      "img": "https://nrk-od-world-17.akamaized.net/open/ps/nnfa/nnfa05052926/e74408c7-23.smil/thumb.jpg?t=1329&scale=480x270&v=high"
    },
    {
      "startTime": 1570,
      "title": "Fisk som matberedskap",
      "img": "https://nrk-od-world-17.akamaized.net/open/ps/nnfa/nnfa05052926/e74408c7-23.smil/thumb.jpg?t=1596&scale=480x270&v=high"
    },
    {
      "startTime": 1697,
      "title": "Teasing dagens sending",
      "img": "https://nrk-od-world-17.akamaized.net/open/ps/nnfa/nnfa05052926/e74408c7-23.smil/thumb.jpg?t=1722&scale=480x270&v=high"
    },
    {
      "startTime": 1799,
      "title": "Åpning 07:00",
      "img": "https://nrk-od-world-17.akamaized.net/open/ps/nnfa/nnfa05052926/e74408c7-23.smil/thumb.jpg?t=1824&scale=480x270&v=high"
    },
    {
      "startTime": 1880,
      "title": "Mener frontfaget fungerer dårlig",
      "img": "https://nrk-od-world-17.akamaized.net/open/ps/nnfa/nnfa05052926/e74408c7-23.smil/thumb.jpg?t=1906&scale=480x270&v=high"
    },
    {
      "startTime": 2011,
      "title": "Heyerdahl om norsk økonomi",
      "img": "https://nrk-od-world-17.akamaized.net/open/ps/nnfa/nnfa05052926/e74408c7-23.smil/thumb.jpg?t=2037&scale=480x270&v=high"
    },
    {
      "startTime": 2279,
      "title": "Fortsatt fare for streik i staten",
      "img": "https://nrk-od-world-17.akamaized.net/open/ps/nnfa/nnfa05052926/e74408c7-23.smil/thumb.jpg?t=2304&scale=480x270&v=high"
    },
    {
      "startTime": 2445,
      "title": "GJEST Før Politisk kvarter",
      "img": "https://nrk-od-world-17.akamaized.net/open/ps/nnfa/nnfa05052926/e74408c7-23.smil/thumb.jpg?t=2471&scale=480x270&v=high"
    },
    {
      "startTime": 2480,
      "title": "Flere skadd da droner traff bygning",
      "img": "https://nrk-od-world-17.akamaized.net/open/ps/nnfa/nnfa05052926/e74408c7-23.smil/thumb.jpg?t=2506&scale=480x270&v=high"
    },
    {
      "startTime": 2654,
      "title": "Overskrifter 07:15",
      "img": "https://nrk-od-world-17.akamaized.net/open/ps/nnfa/nnfa05052926/e74408c7-23.smil/thumb.jpg?t=2679&scale=480x270&v=high"
    },
    {
      "startTime": 2686,
      "title": "Follestad om hockey-bragd",
      "img": "https://nrk-od-world-17.akamaized.net/open/ps/nnfa/nnfa05052926/e74408c7-23.smil/thumb.jpg?t=2711&scale=480x270&v=high"
    },
    {
      "startTime": 2978,
      "title": "Tek-fest på børsen",
      "img": "https://nrk-od-world-17.akamaized.net/open/ps/nnfa/nnfa05052926/e74408c7-23.smil/thumb.jpg?t=3004&scale=480x270&v=high"
    },
    {
      "startTime": 3130,
      "title": "Bekymret for stampuben",
      "img": "https://nrk-od-world-17.akamaized.net/open/ps/nnfa/nnfa05052926/e74408c7-23.smil/thumb.jpg?t=3155&scale=480x270&v=high"
    },
    {
      "startTime": 3365,
      "title": "John Egil (79) jobber frivillig",
      "img": "https://nrk-od-world-17.akamaized.net/open/ps/nnfa/nnfa05052926/e74408c7-23.smil/thumb.jpg?t=3390&scale=480x270&v=high"
    },
    {
      "startTime": 3559,
      "title": "Teasing dagens sending",
      "img": "https://nrk-od-world-17.akamaized.net/open/ps/nnfa/nnfa05052926/e74408c7-23.smil/thumb.jpg?t=3585&scale=480x270&v=high"
    },
    {
      "startTime": 3567,
      "title": "Trailer - MØRCH OG VM",
      "img": "https://nrk-od-world-17.akamaized.net/open/ps/nnfa/nnfa05052926/e74408c7-23.smil/thumb.jpg?t=3593&scale=480x270&v=high"
    },
    {
      "startTime": 3600,
      "title": "Overskrifter 07:30",
      "img": "https://nrk-od-world-17.akamaized.net/open/ps/nnfa/nnfa05052926/e74408c7-23.smil/thumb.jpg?t=3626&scale=480x270&v=high"
    },
    {
      "startTime": 3609,
      "title": "Fortsatt fare for streik i staten",
      "img": "https://nrk-od-world-17.akamaized.net/open/ps/nnfa/nnfa05052926/e74408c7-23.smil/thumb.jpg?t=3634&scale=480x270&v=high"
    },
    {
      "startTime": 3759,
      "title": "Mener frontfaget fungerer dårlig",
      "img": "https://nrk-od-world-17.akamaized.net/open/ps/nnfa/nnfa05052926/e74408c7-23.smil/thumb.jpg?t=3785&scale=480x270&v=high"
    },
    {
      "startTime": 3875,
      "title": "VM-bragd i ishockey",
      "img": "https://nrk-od-world-17.akamaized.net/open/ps/nnfa/nnfa05052926/e74408c7-23.smil/thumb.jpg?t=3900&scale=480x270&v=high"
    },
    {
      "startTime": 3966,
      "title": "Blue Origin-rakett eksploderte",
      "img": "https://nrk-od-world-17.akamaized.net/open/ps/nnfa/nnfa05052926/e74408c7-23.smil/thumb.jpg?t=3991&scale=480x270&v=high"
    },
    {
      "startTime": 4056,
      "title": "Alkohol på hvileplasser",
      "img": "https://nrk-od-world-17.akamaized.net/open/ps/nnfa/nnfa05052926/e74408c7-23.smil/thumb.jpg?t=4081&scale=480x270&v=high"
    },
    {
      "startTime": 4162,
      "title": "Storbrann i Stockholm",
      "img": "https://nrk-od-world-17.akamaized.net/open/ps/nnfa/nnfa05052926/e74408c7-23.smil/thumb.jpg?t=4187&scale=480x270&v=high"
    },
    {
      "startTime": 4180,
      "title": "Mange klager på høy musikk fra russen i natt",
      "img": "https://nrk-od-world-17.akamaized.net/open/ps/nnfa/nnfa05052926/e74408c7-23.smil/thumb.jpg?t=4206&scale=480x270&v=high"
    },
    {
      "startTime": 4200,
      "title": "Åpning 07:40",
      "img": "https://nrk-od-world-17.akamaized.net/open/ps/nnfa/nnfa05052926/e74408c7-23.smil/thumb.jpg?t=4226&scale=480x270&v=high"
    },
    {
      "startTime": 4221,
      "title": "GJEST Stampuben",
      "img": "https://nrk-od-world-17.akamaized.net/open/ps/nnfa/nnfa05052926/e74408c7-23.smil/thumb.jpg?t=4246&scale=480x270&v=high"
    },
    {
      "startTime": 5400,
      "title": "NRK Nyheter 08:00",
      "img": "https://nrk-od-world-17.akamaized.net/open/ps/nnfa/nnfa05052926/e74408c7-23.smil/thumb.jpg?t=5425&scale=480x270&v=high"
    },
    {
      "startTime": 5579,
      "title": "Åpning 08:03",
      "img": "https://nrk-od-world-17.akamaized.net/open/ps/nnfa/nnfa05052926/e74408c7-23.smil/thumb.jpg?t=5604&scale=480x270&v=high"
    },
    {
      "startTime": 5665,
      "title": "Radikalisering barn og unge",
      "img": "https://nrk-od-world-17.akamaized.net/open/ps/nnfa/nnfa05052926/e74408c7-23.smil/thumb.jpg?t=5690&scale=480x270&v=high"
    },
    {
      "startTime": 5866,
      "title": "Nettsekt sprer seg i Norge",
      "img": "https://nrk-od-world-17.akamaized.net/open/ps/nnfa/nnfa05052926/e74408c7-23.smil/thumb.jpg?t=5891&scale=480x270&v=high"
    },
    {
      "startTime": 6013,
      "title": "Flere myke trafikanter dør",
      "img": "https://nrk-od-world-17.akamaized.net/open/ps/nnfa/nnfa05052926/e74408c7-23.smil/thumb.jpg?t=6038&scale=480x270&v=high"
    },
    {
      "startTime": 6130,
      "title": "Trygg Trafikk om ulykker",
      "img": "https://nrk-od-world-17.akamaized.net/open/ps/nnfa/nnfa05052926/e74408c7-23.smil/thumb.jpg?t=6156&scale=480x270&v=high"
    },
    {
      "startTime": 6347,
      "title": "Overskrifter 08:15",
      "img": "https://nrk-od-world-17.akamaized.net/open/ps/nnfa/nnfa05052926/e74408c7-23.smil/thumb.jpg?t=6372&scale=480x270&v=high"
    },
    {
      "startTime": 6396,
      "title": "Fredagspanelet",
      "img": "https://nrk-od-world-17.akamaized.net/open/ps/nnfa/nnfa05052926/e74408c7-23.smil/thumb.jpg?t=6422&scale=480x270&v=high"
    },
    {
      "startTime": 7134,
      "title": "Patrick Thoresen om hockey-bragd",
      "img": "https://nrk-od-world-17.akamaized.net/open/ps/nnfa/nnfa05052926/e74408c7-23.smil/thumb.jpg?t=7159&scale=480x270&v=high"
    },
    {
      "startTime": 7368,
      "title": "Overskrifter 08:30",
      "img": "https://nrk-od-world-17.akamaized.net/open/ps/nnfa/nnfa05052926/e74408c7-23.smil/thumb.jpg?t=7394&scale=480x270&v=high"
    },
    {
      "startTime": 7434,
      "title": "Blue Origin-rakett eksploderte",
      "img": "https://nrk-od-world-17.akamaized.net/open/ps/nnfa/nnfa05052926/e74408c7-23.smil/thumb.jpg?t=7459&scale=480x270&v=high"
    },
    {
      "startTime": 7607,
      "title": "Fortsatt fare for streik i staten",
      "img": "https://nrk-od-world-17.akamaized.net/open/ps/nnfa/nnfa05052926/e74408c7-23.smil/thumb.jpg?t=7632&scale=480x270&v=high"
    },
    {
      "startTime": 7740,
      "title": "Fotballtrøyefredag for Barnekreft",
      "img": "https://nrk-od-world-17.akamaized.net/open/ps/nnfa/nnfa05052926/e74408c7-23.smil/thumb.jpg?t=7765&scale=480x270&v=high"
    },
    {
      "startTime": 8238,
      "title": "Overskrifter 08:45",
      "img": "https://nrk-od-world-17.akamaized.net/open/ps/nnfa/nnfa05052926/e74408c7-23.smil/thumb.jpg?t=8264&scale=480x270&v=high"
    },
    {
      "startTime": 8274,
      "title": "Anmeldelse fra Festspillene i Bergen",
      "img": "https://nrk-od-world-17.akamaized.net/open/ps/nnfa/nnfa05052926/e74408c7-23.smil/thumb.jpg?t=8299&scale=480x270&v=high"
    },
    {
      "startTime": 8496,
      "title": "Bekymret for stampuben",
      "img": "https://nrk-od-world-17.akamaized.net/open/ps/nnfa/nnfa05052926/e74408c7-23.smil/thumb.jpg?t=8521&scale=480x270&v=high"
    },
    {
      "startTime": 8687,
      "title": "Alkohol på hvileplasser",
      "img": "https://nrk-od-world-17.akamaized.net/open/ps/nnfa/nnfa05052926/e74408c7-23.smil/thumb.jpg?t=8713&scale=480x270&v=high"
    },
    {
      "startTime": 8854,
      "title": "GJEST Været i dag",
      "img": "https://nrk-od-world-17.akamaized.net/open/ps/nnfa/nnfa05052926/e74408c7-23.smil/thumb.jpg?t=8879&scale=480x270&v=high"
    },
    {
      "startTime": 8998,
      "title": "Avslutning",
      "img": "https://nrk-od-world-17.akamaized.net/open/ps/nnfa/nnfa05052926/e74408c7-23.smil/thumb.jpg?t=9004.32&scale=480x270&v=high"
    }
  ]
}